{"result": [{"title": "美國第8例！波士頓麻州大學生武漢肺炎確診美東首例| 武漢肺炎全球 ...", "content": "2020年2月2日 ... 麻州公衛部門今日公告，一名波士頓20多歲男子確診新型冠狀病毒肺炎；據波士頓麻\n州大學(UMass Boston)聲明，確認該患者是該校學生，姓名並未 ..."}, {"title": "新冠肺炎「症狀」已經改變！但有2點跟流感最不一樣| Heho健康", "content": "2020年3月23日 ... 新冠肺炎疫情持續延燒，一開始疾管署防疫醫師鄔豪欣認為，流感跟新冠肺炎的症狀\n的確很相似，但「新冠肺炎比較不會肌肉痠痛」，可以用這個來 ..."}, {"title": "咳不停是過敏、流感還是新冠肺炎？專家教你一張表判斷| Heho健康", "content": "2020年3月26日 ... 但是，一般人很難在第一時間判斷，自己的咳嗽究竟是感冒、肺炎或是流感。 美國\n媒體CNN採訪了美國梅奧診所的醫學和傳染病教授格雷格·波蘭（Greg ..."}, {"title": "從武漢到世界 COVID-19（武漢肺炎）疫情即時脈動", "content": "COVID-19（武漢肺炎）疫情發展瞬息萬變，《報導者》串接即時更新的病例資料庫，以\n多媒體地圖、圖表解釋疫情最新發展，更看見台灣本土防疫和科研進展。"}, {"title": "新冠肺炎新紀錄！ 我國首現連七天零確診好成績| 我嚴防新冠肺炎 ...", "content": "1 天前 ... 自1月21日我國出現首例新冠肺炎確診者以來，今天國內第一次迎來連續7天「零確診\n」，累計32天無本土病例。指揮中心指揮官陳..."}, {"title": "1分鐘看懂！新冠肺炎、流感、感冒症狀有何差異| Heho健康", "content": "2020年4月9日 ... 新冠肺炎、感冒、流感主要症狀. 感冒較少引起全身性症狀，主要是鼻水、鼻塞、咳嗽\n等上呼吸道症狀，且不太會發燒，但 ..."}, {"title": "影／美通報新冠肺炎死亡首例川普宣布擴大出國旅行限制| 新冠肺炎 ...", "content": "2020年3月1日 ... 華盛頓州29日通報美國境內出現第一個因新冠肺炎死亡的病例之後，白宮擴大出國\n旅行限制，禁止過去14天到過伊朗的外國人人境，並對義大利和 ..."}, {"title": "5月12日新冠肺炎全球最新情報", "content": "3 天前 ... 2019冠狀病毒疾病（COVID-19，新冠肺炎）疫情大流行，解禁後第二波疫情蠢蠢欲動\n。德國啟動解封，但病毒似乎加速擴散..."}, {"title": "【獨家專訪】台灣首例武漢肺炎確診個案治癒過程！主治醫生獨白：每天 ...", "content": "2020年2月13日 ... 我們面對這次的武漢肺炎，很多時候都是在跟『人性』做抗爭，你的恐懼感、猜忌心、\n配合度、你的信心、醫護人員的勇氣，天天都是面對自己的心情 ..."}, {"title": "中共堅持不可叫「武漢肺炎」的荒謬與缺乏反省的劣根性| u 值媒", "content": "2020年2月8日 ... 中共堅持俗稱「祖國肺炎」的武漢肺炎不可以叫武漢肺炎，要叫新冠病毒，出動紅媒\n力量在華文世界狂洗，甚至遊說和向WHO施壓，已經成為一場國際 ..."}, {"title": "中共堅持不可叫「武漢肺炎」的荒謬與缺乏反省的劣根性| u 值媒", "content": "2020年2月8日 ... 中共堅持俗稱「祖國肺炎」的武漢肺炎不可以叫武漢肺炎，要叫新冠病毒，出動紅媒\n力量在華文世界狂洗，甚至遊說和向WHO施壓，已經成為一場國際 ..."}, {"title": "美國防部簡報示警新冠肺炎恐30天內全球大流行| 新冠肺炎全球燒 ...", "content": "2020年3月3日 ... 根據「新聞週刊」（Newsweek）取得的參謀首長聯席會議（Joint Chiefs of Staff）每日\n情報摘要指出，2019年冠狀病毒疾病（COVID-19，新冠肺炎）將在 ..."}, {"title": "新冠肺炎的「輕症患者」居多，這是好事還是壞事？ | Heho健康", "content": "2020年3月5日 ... 新冠肺炎（COVID-19）的疫情持續延燒，在12月初爆發第一起病例以來，不過2、3個\n月的時間，全球感染人數已經超越2003年SARS的所有病例；中國 ..."}, {"title": "新冠肺炎全球最新情報5/15", "content": "14 小時前 ... 2019冠狀病毒疾病（COVID-19，武漢肺炎）疫情大流行，世界衛生組織警告，新型\n冠狀病毒恐怕會像愛滋病毒一樣永遠無法..."}, {"title": "新冠肺炎快速擴散美國防疫專家：擔心台灣防堵策略可能失效| 雜誌 ...", "content": "2020年2月20日 ... 17年前SARS期間負責流行病應變，前美國疾病防治中心主任阿里．可汗接受《天下》\n專訪，預測新冠肺炎的疫情走向，並提醒台灣仍要小心謹慎，因為 ..."}, {"title": "美當局示警，中國企圖竊取武漢肺炎疫苗研究| TechNews 科技新報", "content": "1 天前 ... 美國當局13 日警告醫護與科研人員，中國支持的駭客正企圖竊取與2019 新型冠狀\n病毒（COVID-19，武漢肺炎）治療方法和疫苗相關的研究和智慧 ..."}, {"title": "新冠肺炎症狀一變再變！小孩、老人、中年人的症狀有什麼差？ | Heho ...", "content": "2020年4月3日 ... 新冠肺炎疫情持續延燒，全世界已經突破21萬人確診，而且症狀不斷改變，從一開始\n的流感症狀，到出現心臟感染、嗅覺、味覺的失調，現在甚至開始 ..."}, {"title": "美國新冠肺炎確診病例逾8.2萬例超越大陸成全球最多| 新冠肺炎全球燒 ...", "content": "2020年3月27日 ... 根據美國約翰霍普金斯大學最新發布的數據顯示，截至台北時間27日6時20分，美國\n新冠肺炎確診病例升至82404例，超越中國大陸成為確診數最高 ..."}, {"title": "武漢肺炎全球最新情報5/13 | 國際| 重點新聞| 中央社CNA", "content": "2 天前 ... 2019冠狀病毒疾病（COVID-19，武漢肺炎）疫情大流行，俄羅斯確診總數躍居全球第\n2。受疫情影響，中華民國棒球協會上週接獲美職大聯盟通知， ..."}, {"title": "約翰·霍普金斯大學發表可追蹤武漢肺炎災情的即時地圖| iThome", "content": "2020年1月28日 ... 這個名為Wuhan Coronavirus Global Cases的網站，透過蒐集媒體、社群、官方等\n多種資訊源，在全球地圖上呈現了武漢肺炎確診及死亡人數的即時 ..."}, {"title": "卡介苗可抗新冠肺炎？以色列60萬人研究曝光醫給出解釋- Yahoo奇摩 ...", "content": "7 小時前 ... 卡介苗對新冠肺炎是否有顯著防護效果？這個可能性讓美國哈佛大學與眾多研究\n單位相當好奇並展開研究。而這一疑惑近期被以色列一項統計多 ..."}, {"title": "中國第二波肺炎來襲？吉林市宣布封城| Anue鉅亨- 大陸政經", "content": "1 天前 ... 自上周吉林省舒蘭市新冠肺炎爆發社區感染後，疫情似乎開始有向外擴散的跡象，\n吉林市也跟進出現境內傳染案例。吉林市政府周三(13 日) 宣布全面 ..."}, {"title": "紐約州新冠肺炎再添758死累計9385人病故美國確診逾55萬人| 新冠 ...", "content": "2020年4月13日 ... 美國紐約州州長古莫（Andrew Cuomo）今天指出，過去24小時內紐約州又有758名\n新冠肺炎患者不治，全州累計9385人病故。"}, {"title": "台團隊找出治武漢肺炎中藥方最快8天驗無病毒【獨家】 | 生活| 重點新聞 ...", "content": "4 天前 ... 武漢肺炎延燒全球，中國大陸、韓國紛紛投入中藥療法研發，台灣研究團隊沿用\nSARS治療經驗找出獨門中藥配方，初步研究可在8到10天內清除體內 ..."}, {"title": "新冠肺炎「疫苗」不是最佳解！台灣病毒學權威點出4原因| Heho健康", "content": "5 天前 ... 免疫過度反應是死亡關鍵. 大約10 至14％的人會比較嚴重，有肺炎及呼吸困難的\n問題，主要是巨噬細胞的量不足 ..."}, {"title": "武漢肺炎連6天零確診連31天無本土病例| 生活| 重點新聞| 中央社CNA", "content": "2 天前 ... 中央流行疫情指揮中心為因應武漢肺炎疫情，今天下午2時召開記者會，說明疫情及\n防疫作為等事宜。"}, {"title": "維穩凌遲真相的中國故事：揭發武漢肺炎「吹哨人醫師」李文亮病逝 ...", "content": "2020年2月7日 ... 被當造謠的求救真話：揭發武漢肺炎，中國「吹哨人醫師」李文亮病逝. 「政府欠李文亮\n醫師一個永遠遲到的道歉。」武漢新型冠狀病毒的中國疫情，6日 ..."}, {"title": "武漢肺炎／似流感又可能無症狀！一分鐘內了解5大新冠病毒重點 ...", "content": "2020年3月19日 ... 武漢肺炎確診個案越來越多，根據ＷＨＯ最新公佈的前十大患者的症狀，前三項就是\n發燒、乾咳、倦怠，和感冒、流感都極為相似，甚至越來越多無症狀 ..."}, {"title": "拿武漢肺炎歧視黃種人！歐洲霸凌總動員無法想像… | 武漢肺炎全球燒 ...", "content": "2020年1月31日 ... 武漢肺炎疫情持續在全球延燒，某些西方國家的亞裔居民因此遭受前所未見的公開\n歧視。"}, {"title": "台灣第18例新冠肺炎病患台首見無症狀高病毒量案例| 我嚴防新冠肺炎 ...", "content": "2020年2月9日 ... 台灣一家四口經香港轉機，到義大利自由行，返台後父母及20多歲哥哥先後都有出現\n症狀並確診為新冠肺炎確診，指揮中心高度懷疑2..."}, {"title": "武漢肺炎疫情更新：全美24州+特區進入緊急狀態| Anue鉅亨- 國際政經", "content": "2020年3月11日 ... 1、WHO 每日疫情報告：3 月11 日，除中國外，全球共有113 國出現武漢肺炎病例，新\n增病例數較前一日增加4596 例，累計達37371 例；死亡病例比前 ..."}, {"title": "打疫苗能預防「武漢肺炎」嗎？醫：降低重症致死風險！ | Heho健康", "content": "2020年1月21日 ... 源自武漢的新型肺炎近日疫情愈演愈烈，不僅中國大陸多個城市傳出疫情，包括韓國\n、泰國等東亞國家也陸續傳出疾病，令人擔憂的是冠狀病毒不但 ..."}, {"title": "武漢肺炎》台灣幸福指數爆表！台大教授舉一國慘況對比| 生活| 新頭殼 ...", "content": "11 小時前 ... 徐丞志在個人臉書表示，這幾天台灣已經沒怎麼在關注covid-19（武漢肺炎、新冠\n肺炎），中央指揮中心的記者會也已經沒什麼收視率，「反而是新科立 ..."}, {"title": "埃及遊船12人染新冠肺炎控台人是感染源指揮中心回應| 新冠肺炎全球 ...", "content": "2020年3月6日 ... 據外媒報導，埃及一艘尼羅河遊船上發生12名船員確診新冠肺炎，疑遭一名台籍遊客\n感染。中央流行疫情指揮中心表示，我國案39研..."}, {"title": "第二波感染潮？台灣連續好幾天零確診大陸、南韓、德國卻紛紛傳出 ...", "content": "台灣新冠肺炎疫情趨緩，已經連續好幾天零確診，且無本土案例，中央流行疫情指揮\n中心也開始鬆綁防疫禁令、逐步解封。但近日卻傳出中國大陸的武漢、吉林、南韓 ..."}, {"title": "武漢肺炎》台裔美籍女機師運送防疫物資在印尼墜機喪命- 國際- 自由 ...", "content": "1 天前 ... 首次上稿00:48更新時間06:01台裔美籍女飛行員Joyce Lin運送武漢肺炎（新型冠狀\n病毒病，COVID-19）防疫物資給印尼偏鄉，12日不幸在飛機起飛 ..."}, {"title": "陸導演常凱1家4口新冠肺炎亡陸媒揭17天「煉獄過程」", "content": "2020年2月17日 ... 大陸新冠肺炎疫情肆虐，傳出一件又一件悲傷的案例，大陸導演常凱一家4口染新冠\n肺炎先後去世，疾病導致家破人亡，有陸媒揭露了他..."}, {"title": "美國新冠肺炎患者出現「腦部壞死病變」！專家：比發燒、咳嗽症狀更早 ...", "content": "2020年4月13日 ... 新冠肺炎症狀不斷改變，從一開始的流感症狀，到出現心臟感染、嗅覺、味覺的失調，\n現在甚至開始有腦部病變的產生，而且在短短幾小時內就可能 ..."}, {"title": "我又增兩新冠肺炎確診者24例的女兒、孫女中鏢| 我嚴防新冠肺炎| 要聞 ...", "content": "2020年2月21日 ... 中央流行疫情指揮中心今（21）日公布新增2例新冠肺炎（COVID-19）病例，為案24\n外孫女（案25，20歲）及小女兒（..."}, {"title": "武漢肺炎全球最新情報5/15 | 國際| 重點新聞| 中央社CNA", "content": "15 小時前 ... 2019冠狀病毒疾病（COVID-19，武漢肺炎）疫情大流行，世界衛生組織警告，新型\n冠狀病毒恐怕會像愛滋病毒一樣永遠無法消滅。疫情衝擊經濟，預估 ..."}, {"title": "大陸宣布：武漢肺炎英文簡稱為「NCP」 | 陸武漢肺炎疫情| 要聞| 聯合 ...", "content": "2020年2月8日 ... 針對此波武漢肺炎如何稱呼，中國國家衛生健康委員會今天在官網公告，暫時命名「\n新型冠狀病毒肺炎」、簡稱「新冠肺炎」；英文「Novel Coronavirus ..."}, {"title": "法國去年11月就出現新冠肺炎患者比已知再早1個月| 新冠肺炎全球燒 ...", "content": "2020年5月8日 ... 院方7日發布新聞稿指出：「去年11月16日本中心發現法國新冠肺炎首例。起初病毒\n傳播非常慢，直到今年2月底才迅速傳開，3月底達到高峰。」 巴黎東北 ..."}, {"title": "疫情最新：中國新冠肺炎死亡人數破2,000人| 陸新冠肺炎疫情| 要聞 ...", "content": "2020年2月19日 ... 湖北衛健委發布疫情公告，2020年2月18日0至24時，全省新增新冠肺炎確診病例\n1693例，全省新增病亡132例。"}, {"title": "武漢肺炎破2萬感染：中國譴責美國散播恐慌，但同意美方專家馳援 ...", "content": "2020年2月4日 ... 2月4日，中國／美國。「WHO說世界反應過度，根本沒必要封關管控。」中國的武漢\n肺炎疫情，4日情況持續失控。根據官方的統計數據，中國境內 ..."}, {"title": "全球首例！三組專家鑑定香港新冠肺炎病患寵物狗也確診| 陸新冠肺炎 ...", "content": "2020年3月4日 ... 新冠肺炎疫情持續，本港今日（4日）出現相信是全球首宗狗隻感染個案。漁農自然\n護理署表示，第85宗確診個案、馬主周巧兒的寵物松鼠狗，口腔及 ..."}, {"title": "中國網軍年後拼復工，以武漢肺炎議題為餌，鎖定臺灣政府和醫療智庫 ...", "content": "2020年4月23日 ... 即使世界因為武漢肺炎擴散，導致許多國家或城市被封鎖而暫停，但網路世界確依然\n熱鬧，TeamT5杜浦數位安全執行長蔡松廷（網路暱稱TT）於4 ..."}, {"title": "白宮成病毒溫床！副總統彭斯助手罹患新冠肺炎| Anue鉅亨- 國際政經", "content": "6 天前 ... 白宮確診案例連環爆，美國總統川普的助手週四甫傳出罹患新冠肺炎後，週五(8 日) \n美國副總統彭斯的助手也確診染疫。"}, {"title": "武漢肺炎首度連7天零確診連32天無本土病例| 生活| 重點新聞| 中央社 ...", "content": "1 天前 ... 中央流行疫情指揮中心宣布，台灣今天無新增武漢肺炎（2019冠狀病毒疾病，COVID-\n19）確診，這是首度連7天零確診，打破2度止步「連6」魔咒，目前 ..."}, {"title": "全球新冠肺炎疫情突破28萬死確診超過407萬例| 新冠肺炎全球燒| 要聞 ...", "content": "4 天前 ... 法新社彙整的官方數據顯示，截至格林威治標準時間10日19時（台灣11日凌晨3時），\n全球至少28萬693人死於2019冠狀..."}, {"title": "拉肚子恐是武漢肺炎症狀之一？張上淳：將決定是否納入通報- Yahoo ...", "content": "2020年4月2日 ... 狡猾的武漢肺炎病毒，竟讓國內15個武漢肺炎患者完全沒症狀的比例接近5%，甚至\n曾有無症狀患者兩周後才被確診，病毒還疑似讓越來越多患者 ..."}, {"title": "紐約武漢肺炎累計死亡破萬州長：最糟階段已過| 國際| 重點新聞 ...", "content": "2020年4月14日 ... 美國紐約州單日671人因感染武漢肺炎喪命，累計死亡破萬，但住院、插管患者數量\n基本持平。州長古莫自疫情爆發以來首次宣告最糟階段已過，同時 ..."}, {"title": "【不斷更新】《權遊》男星確診新冠肺炎！這些名人都得了新冠肺炎 ...", "content": "2020年3月17日 ... 新冠肺炎COVID-19 在全球疫情病例不斷上升，尤其連好萊塢多位影星也確診，包含\n奧斯卡影帝湯姆漢克斯（Tom Hanks）與老婆在澳洲證實確診； ..."}, {"title": "美國新冠肺炎逾7萬死確診逼近120萬例| 新冠肺炎全球燒| 要聞| 聯合 ...", "content": "2020年5月6日 ... 根據路透社統計，美國的2019冠狀病毒疾病（COVID-19，武漢肺炎）死亡病例已破7\n萬，是世界病故人數最多的國家."}, {"title": "〈新冠肺炎疫情〉防疫、宅經濟、轉單效應一文看懂台廠三大受惠概念股 ...", "content": "2020年2月4日 ... 中國武漢肺炎疫情持續延燒，口罩、耳溫槍、清潔用品等防疫相關產品成為搶手貨，\n除了防疫概念股成為鼠年開紅盤的焦點，宅經濟概念股也順勢引發 ..."}, {"title": "德國鬆綁防疫社交限制新冠肺炎又加速擴散| 新冠肺炎全球燒| 要聞 ...", "content": "5 天前 ... 德國領袖鬆綁防疫社交限制幾天後，2019冠狀病毒疾病（COVID-19，新冠肺炎）感染\n人數增加速度又變快，令人憂心疫情可..."}, {"title": "新冠肺炎疫情迅速蔓延全球股市為何沒大跌？ | 全球財經| 全球| 聯合 ...", "content": "2020年2月11日 ... 受新冠肺炎（武漢肺炎）疫情衝擊，中國大陸股市在農曆春節長假過後暴跌，連帶拖累\n各國股市走低，但全球股市迅速反彈，美股大盤道瓊工業指數 ..."}, {"title": "我國現首例遭美籍人士感染本土新冠肺炎出現症狀友人已離境| 我嚴防 ...", "content": "2020年3月13日 ... 中央流行疫情指揮中心今日公布國內第50例新冠肺炎病例，為中部50多歲美國籍\n男性，獨自在台工作，2月24日曾接待4名來台的..."}, {"title": "平均25歲中研院團隊14天合成純度97%新冠肺炎用藥| 我嚴防新冠肺炎 ...", "content": "2020年2月21日 ... 新冠肺炎（COVID-19）疫情持續，我政府邀集國衛院等多個單位合成有望治療武漢\n肺炎的藥物瑞德西韋。中研院化學所平均約2..."}, {"title": "武漢肺炎2日新增3例達432例連20天無本土病例[影] | 生活| 重點新聞 ...", "content": "2020年5月2日 ... 中央流行疫情指揮中心今天宣布，台灣新增3例境外移入武漢肺炎確診個案，皆為\n境外移入，都是在機場檢疫採檢通報攔截。其中2人為一對夫婦，其2 ..."}, {"title": "染疫身亡司機2親人確診新冠肺炎台灣累計22例| 我嚴防新冠肺炎| 要聞 ...", "content": "2020年2月17日 ... 中央流行疫情指揮中心剛剛日公布國內新增2例COVID-19(武漢肺炎)病例，為中部\n80多歲女性(案21)及30多歲男性(..."}, {"title": "紐約動物園老虎染武漢肺炎疑無症狀保育員傳染| 國際| 重點新聞 ...", "content": "2020年4月6日 ... 美國紐約市布朗克斯動物園今天表示，園內一隻老虎驗出對2019冠狀病毒疾病（\nCOVID-19，武漢肺炎）呈陽性反應，據信是被一名無症狀的保育員 ..."}, {"title": "武漢肺炎正名COVID-19 世衛：18 個月後誕首支疫苗| Anue鉅亨- 國際 ...", "content": "2020年2月11日 ... 世界衛生組織(WHO) 週二正式將武漢肺炎的英文名稱定為COVID-19，CO 代表冠狀\n，VI 代表病毒，D 代表疾病，19 代表於2019 年發現。 早前世衛的《 ..."}, {"title": "武漢肺炎讓美國人禁足在家，庭院種植蔬果正夯| TechNews 科技新報", "content": "2020年4月18日 ... 在美國，為預防武漢肺炎疫情持續擴大，許多州已經頒布「禁足令」要求民眾非必要\n不得外出，學校也會停課至5 月。由於國家進入緊急狀態，全美各地 ..."}, {"title": "你的足跡有跟新冠肺炎患者重疊嗎？網站簡單4步驟馬上測| 我嚴防 ...", "content": "2020年3月2日 ... 新冠肺炎疫情讓民眾人心惶惶，由一群程式設計師發起的台灣線上社群「g0v」推出\n一個可以檢查你是否接觸過肺炎患者的網站，只要有開啟手機 ..."}, {"title": "【新冠肺炎/不斷更新】台灣連8天「零新增」 33天無本土病例- Yahoo奇摩 ...", "content": "9 小時前 ... 不過今天巴西衛生部更新疫情報告，過去24小時巴西2019冠狀病毒疾病（COVID-19\n，武漢肺炎）新增844例死亡、1萬3944例確診；累計1萬3993例死亡 ..."}, {"title": "新冠肺炎疫情蔓延郵輪難獲准靠岸乘客苦中作樂| 新冠肺炎全球燒 ...", "content": "2020年2月13日 ... 因俗稱武漢肺炎的2019年冠狀病毒疾病（COVID-19）疫情蔓延人心惶惶，亞洲多國\n拒絕郵輪「威士特丹號」靠岸，船上苦中..."}, {"title": "新冠肺炎肆虐美國死亡突破2萬大關冠全球| 新冠肺炎全球燒| 要聞 ...", "content": "2020年4月12日 ... 根據約翰霍普金斯大學（Johns Hopkins University）統計，美國境內感染2019冠狀\n病毒疾病（COVID-19，武漢肺炎）不治人數今天突破2萬大關，取代 ..."}, {"title": "3D 成像看武漢肺炎病毒可怕之處：無症狀感染數天，肺部就多處受損 ...", "content": "2020年3月27日 ... 最近，美國喬治‧華盛頓大學醫院發表武漢肺炎病毒感染肺部後的3D 成像影片，影片\n患者直到幾天前都沒有咳嗽、發燒等症狀，然而影片已能清楚看見 ..."}, {"title": "傳美打算指控中國意圖駭取疫苗資料，武漢肺炎左右情資戰 ...", "content": "4 天前 ... 武漢肺炎成為大流行病，率先研發出疫苗的國家，將握有人民健康的籌碼，制肘敵國。\n也就是說，疫苗研發已成為中美戰略行動。武漢肺炎如今左右資 ..."}, {"title": "美國武漢肺炎死亡新增逾千例確診逼近百萬大關| 國際| 重點新聞 ...", "content": "2020年4月28日 ... 根據約翰霍普金斯大學今晚最新統計數據，美國過去24小時內2019冠狀病毒疾病（\nCOVID-19）疫情新增1303起死亡病例，確診病例總數逼近100萬 ..."}, {"title": "肺炎讓全世界都反中？日本民眾這些話讓台灣立場好尷尬... | 新冠肺炎 ...", "content": "2020年2月16日 ... 新冠肺炎疫情爆發後，國際社會就出現不少針對中國的歧視性言論，但日本厚生勞動\n省官員公開表示，「壞的是病毒，而非人。」東京地標天空樹還特別 ..."}, {"title": "武漢肺炎專家同聲示警，全球經濟到底多危險| TechNews 科技新報", "content": "2020年3月8日 ... 武漢肺炎疫蔓延全球，不只美國聯準會緊急宣布降息2 碼，經濟暨發展組織（OECD）\n更一舉將2020 年全球經濟成長預估值調降至2.4%，為金融危機 ..."}, {"title": "美國首起人傳人！新增一武漢肺炎確診為第2例病患配偶| 武漢肺炎 ...", "content": "2020年1月31日 ... 美國疾病控制與預防中心（CDC）30日宣布，伊利諾州新增一例武漢肺炎確診病例，\n是先前確診第二例境外移入個案的配偶，為美國..."}, {"title": "新冠肺炎疫情下的「安全國家」排名德國名列第二| 新冠肺炎全球燒 ...", "content": "新冠肺炎疫情下的「安全國家」排名德國名列第二. 2020-04-15 19:40 德國之聲/ 德國\n之聲 德國. 根據設址倫敦的智庫「深度認知（Deep Knowledge Group）」發布的一份 ..."}, {"title": "湯姆漢克斯確診武漢肺炎：好萊塢澳洲拍片的感染危機？ | 過去24小時 ...", "content": "2020年3月12日 ... 湯姆漢克斯確診武漢肺炎：好萊塢澳洲拍片的感染危機？ 「我們確診病毒了。大家\n保重！」正在澳洲拍攝新片的好萊塢影星湯姆漢克斯（Tom Hanks），12 ..."}, {"title": "新冠肺炎第45例為出院病患醫院群聚8人感染| 我嚴防新冠肺炎| 要聞 ...", "content": "2020年3月6日 ... 中央流行疫情指揮中心指揮官陳時中今日公布，國內新增第45例新冠肺炎確診病例，\n為案34確診前同病房、不同病室已出院的病人，..."}, {"title": "國內新增武漢肺炎2例本土個案，相關接觸者持續掌握中- 衛生福利部", "content": "於1月27日出現咳嗽，2月3日因呼吸急促赴醫院就醫，診斷為肺炎。當日收治於負壓\n加護病房治療，個案已於2月15日晚間因肺炎合併敗血症死亡，其遺體經家屬同意，\n將 ..."}, {"title": "新冠肺炎死者解剖報告公開！專家曝與SARS病變最大差異| 陸新冠 ...", "content": "2020年2月28日 ... 中國專家解剖新冠肺炎患者遺體發現，病毒主要引起深部氣道和肺泡損傷為主要特徵\n的炎症反應；遺體穿刺則顯示，肺炎與SARS..."}, {"title": "我新增一新冠肺炎確診病例60歲女性無接觸史、近2年未出國| 我嚴防 ...", "content": "2020年2月19日 ... 中央流行疫情指揮中心今(19)日公布國內第24例COVID-19(武漢肺炎)確定病例，為\n北部60多歲女性，近2年無出國史..."}, {"title": "武漢肺炎連8天零確診連33天無本土病例| 生活| 重點新聞| 中央社CNA", "content": "9 小時前 ... （中央社記者張茗喧、余曉涵台北15日電）中央流行疫情指揮中心指揮官陳時中今天\n宣布，台灣沒有新增武漢肺炎（2019冠狀病毒疾病，COVID-19）確診 ..."}, {"title": "武漢肺炎／美加州憂逾半人口染疫州長要4000萬民眾避免出門| 國際 ...", "content": "2020年3月20日 ... 加州驚人預估州內逾半數人口恐染武漢肺炎. （中央社洛杉磯19日綜合外電報導）美國\n加州州長紐松在疫情持續延燒之際，揭露一項令人擔憂 ..."}, {"title": "新冠肺炎病毒能在物體表面存活多久？NIH研究告訴您| 雜誌| 聯合新聞網", "content": "2020年3月16日 ... 新冠肺炎疫情持續在全球肆虐，為了了解新型冠狀病毒（Covid-19）的傳播力究竟有\n多強，美國研究人員將病毒嘗試性散布在家庭和醫院常見的7 種 ..."}, {"title": "課堂提中華民國、武漢肺炎遭陸生檢舉老師被要求道歉| 大學研究所 ...", "content": "4 天前 ... 中原大學生物科技系副教授招名威表示，他在課中曾提及「武漢肺炎」，及稱自己為「\n中華民國的教授」，引發陸生的不滿，被校方要求道歉。 何志偉說，招 ..."}, {"title": "英國研究：新冠肺炎害死者平均「少活13年」 | 新冠肺炎全球燒| 要聞 ...", "content": "2020年5月2日 ... 新冠病毒至今已奪走全球超過21萬人的性命。最近英國一項研究指出，因為新冠肺炎\n，平均每位男性死者少活13年，女性死者少活11年。"}, {"title": "肺炎後遺症：美中即將掀起「審計大戰」？ | 徐子軒| 鳴人堂", "content": "2020年3月23日 ... 當2019冠狀病毒疾病（COVID-19，新冠肺炎）成為全球流行病之時，各國政府無不如\n臨大敵，絞盡心思面對疫情。除了構成人體健康和公共衛生的 ..."}, {"title": "全球新冠肺炎確診數破100萬例逾5萬人死亡", "content": "2020年4月3日 ... 歐美新冠肺炎疫情不斷升溫，至台北時間3日4時止，根據美國約翰霍普金斯大學疫情\n統計，全球新冠肺炎病故人數已突破5萬例，來到5萬1335人。"}, {"title": "死亡病例突破2.4萬？中媒或意外洩露武漢肺炎真正的數據| Anue鉅亨 ...", "content": "2020年2月5日 ... 外媒週三(5 日) 報導，中國媒體可能手握武漢肺炎兩種數據，一種是真實數據，另\n一種是已處理的數據。"}, {"title": "想到台大確認是否罹武漢肺炎？院方呼籲先看懂分流原則| 我嚴防武漢 ...", "content": "2020年1月29日 ... 台大醫院今起門診全面恢復正常開診，為了避免武漢肺炎潛在病例混雜於就醫人潮，\n引起交叉感染，台大醫院比照SARS當年措施，正..."}, {"title": "美國安顧問：新冠肺炎病毒可能來自武漢實驗室或市場| 新冠肺炎全球 ...", "content": "2 天前 ... 美國白宮國安顧問歐布萊恩今天表示，新冠肺炎病毒來自武漢，有間接證據顯示可能\n來自實驗室或活禽市場，但不論病毒來自哪一個，對..."}, {"title": "新冠肺炎香港家族邀中國親友吃火鍋9人遭感染| 陸新冠肺炎疫情| 要聞 ...", "content": "2020年2月9日 ... 武漢肺炎持續擴散，香港今天出現9名家庭成員同遭感染的疫情，起因是20餘名家族\n成員春節期間聚餐吃火鍋，其中包括來自中國的2..."}, {"title": "好消息！新冠肺炎病例再增三名出院| 我嚴防新冠肺炎| 要聞| 聯合新聞網", "content": "2020年2月23日 ... 中央流行疫情指揮中心今宣布新增3名新冠肺炎確診病人出院，分別是第4例、第5例\n、第12例。指揮中心監測應變官莊人祥表示，之..."}, {"title": "武漢肺炎3日再現零確診連續21天無本土病例| 生活| 重點新聞| 中央社 ...", "content": "2020年5月3日 ... 根據疾管署新聞稿內容，中央流行疫情指揮中心今（3）日表示，國內今日無新增確診\n病例；昨（2）日新增381例新型冠狀病毒肺炎相關通報，截至目前累計 ..."}, {"title": "武漢肺炎／陸客來台限制對象擴大新增在海外、港澳之陸籍人士| 我 ...", "content": "2020年1月27日 ... 武漢肺炎疫情增，中國各省確診個案數快速增加。為因應中國大陸新型冠狀病毒肺炎\n疫情之病例數持續增加，中央流行疫情指揮中心今傍..."}, {"title": "聞之色變的武漢肺炎對全球經濟造成那些影響？ | 全球財經| 全球| 聯合 ...", "content": "2020年2月3日 ... 彭博資訊報導，連結緊密的全球經濟，已開始感受中國大陸新型冠狀病毒（武漢肺炎）\n的衝擊，全球經濟的損失，可能高達1600億..."}, {"title": "武漢華南海鮮市場非新冠肺炎病毒發源地早在去年11月人傳人| 陸新冠 ...", "content": "2020年2月22日 ... 造成這次蔓延全球的新冠肺炎武漢華南海鮮市場，有可能不是病毒發源地！"}, {"title": "因應當局消音，中國網友發起保存武漢肺炎言論活動| iThome", "content": "2020年3月5日 ... 中國網路主管機關要求微信、騰訊、字節跳動等網路平臺，阻擋武漢肺炎消息的散布，\n對此有中國網友在GitHub發起「2020新冠肺炎記憶」專案， ..."}, {"title": "嬌生武漢肺炎疫苗9月展開人體試驗股價大漲8% | Anue鉅亨- 美股", "content": "2020年3月30日 ... 嬌生公司(JNJ-US) 週一(30 日) 表示，9 月將開始為武漢肺炎實驗性疫苗進行人體\n試驗，最快2021 年初可在2021 年初獲美國當局授權用於緊急用途 ..."}, {"title": "華爾街超狂言論：若人人感染武漢肺炎可以拯救經濟| Anue鉅亨- 國際 ...", "content": "2020年3月6日 ... CNBC 芝加哥證交所駐點編輯桑塔利(Rick Santelli) 週五放出驚人言論表示，人人都\n應該得到武漢肺炎，以減輕疫情對經濟的影響。 桑塔利建議：「當然 ..."}, {"title": "武漢肺炎／好消息！10位確診一位即將痊癒，其他康復良好| Heho健康", "content": "2020年2月1日 ... ... 身體壯況都非常好，除了只有一位還有稍微發燒，照過Ｘ光後，肺炎也越來越小。\n只有首位確診個案，呼吸狀態較不穩定，其餘呼吸的狀況都非常好。"}, {"title": "防堵武漢肺炎襲台！陸客限制變嚴剩陸生、配偶可來台| 我嚴防武漢 ...", "content": "2020年1月25日 ... 為有效防治武漢肺炎入台，內政部移民署國境事務大隊今天公布最新入境規定，即日\n起居住地為湖北省的大陸人士，除了陸生就學、台灣..."}]}