{"result": [{"title": "韓國沒有你想像的美好！雪莉、具荷拉自殺背後的殘酷真相| 魯皓平 ...", "content": "2019年11月25日 ... 兩年前，SHINee鐘鉉燒炭自殺，留下了「憂鬱症漸漸吞噬了我，再也無法承受下去」的\n遺書；演員崔真實和崔真永姊弟，也因受不了網路謠言的困擾和 ..."}, {"title": "35個工程師之死：法國電信「職場霸凌自殺潮」的世紀審判| 文化視角 ...", "content": "2019年11月13日 ... 2007至2010年間，「法國電信」（France Telecom）至少有35名員工，疑因遭到公司\n系統性的職場霸凌自殺身亡。圖為2009年，法國電信員工抗議公司 ..."}, {"title": "涉嫌為名人安排性派對艾普斯坦獄中自殺| 美國新聞| 全球| 聯合新聞網", "content": "2019年8月10日 ... 紐約時報10日報導，涉嫌仲介賣淫的艾普斯坦（Jeffrey Epstein）在紐約曼哈坦監獄\n上吊自殺，獄方在10日上午..."}, {"title": "鏡頭背後／梵谷死亡之謎？「自殺手槍」巴黎拍賣會高價賣出| 過去24 ...", "content": "2019年6月20日 ... 這是藝術史上最著名的武器！」這把生鏽的手槍，據信是荷蘭後印象派畫家文森．梵\n谷（Vincent van Gogh），於1890年自殺時所使用的左輪手槍。"}, {"title": "又失言！柯文哲：自殺拜託吃安眠藥，不要自焚| 政治| 要聞| 聯合新聞網", "content": "2019年10月18日 ... 台北市柯文哲昨晚參加打臉名嘴粉絲見面會，談到關心社會邊緣人，引用火災發生\n統計指出很多是自焚，柯文哲說，自殺拜託去河濱公園..."}, {"title": "父因她追星自殺亡劉德華狂粉12年後說「後悔了」 | 大陸傳真| 兩岸| 聯合 ...", "content": "2019年11月5日 ... 劉德華瘋狂粉絲楊麗娟當年迷戀劉德華到走火入魔的地步，2007年楊麗娟的父親因\n女兒過度追星自殺而亡。12年過去，楊麗娟接受..."}, {"title": "法國警察鬧自殺潮黃背心周周暴力示威惹的禍？ | 世界萬象| 全球| 聯合 ...", "content": "2019年8月21日 ... 法國警察自殺率近年不斷攀升，最近又有3名鎮暴警察、1名警察指揮官與1名警察\n學校老師等8人輕生，使得今年至8月18日為止的警察自殺人數 ..."}, {"title": "「我有不快樂的靈魂」 在波登自殺之外，我們沒...｜天下雜誌", "content": "2018年6月9日 ... 《波登闖異地》節目主持人波登（Anthony Bourdain）8日晚間被證實已自殺身亡。3天\n前，美國包包配件品牌創辦人Kate Spade卸下了多年來與憂鬱症纏 ..."}, {"title": "華為公主遭逮捕丹華資本張首晟自殺全球5G戰暗潮洶湧- 今周刊", "content": "2018年12月12日 ... 張首晟是史丹佛大學教授、中國科學院外籍院士、競逐諾貝爾物理獎的熱門人選，卻\n加入了中國高官、軍頭、國營企業董事長「自殺、被自殺」的行列。"}, {"title": "影／畏罪自殺？ 大馬女華僑分屍案兇嫌陳屍基隆民宅", "content": "2020年1月12日 ... 台北市26歲鄧姓女華僑慘遭殺害分屍，45歲林姓男子涉有重嫌，今晚6時許，基隆市\n消防局接獲百三街有人燒炭自殺，經確認就是林..."}, {"title": "影／畏罪自殺？ 大馬女華僑分屍案兇嫌陳屍基隆民宅", "content": "2020年1月12日 ... 台北市26歲鄧姓女華僑慘遭殺害分屍，45歲林姓男子涉有重嫌，今晚6時許，基隆市\n消防局接獲百三街有人燒炭自殺，經確認就是林..."}, {"title": "25歲就被嫌太老…具荷拉之死揭韓演藝圈黑暗面| 世界萬象| 全球| 聯合 ...", "content": "2019年11月27日 ... 前韓國女團Kara成員具荷拉24日在住處自殺身亡，是繼27歲SHINee主唱金鐘鉉和\n前女團f(x)成員雪莉（Sulli）之後，又一名韓星輕生。紐約時報指出， ..."}, {"title": "香港15歲少女離奇成浮屍母親：女兒是自殺的| 香港反送中抗爭| 兩岸 ...", "content": "2019年10月17日 ... 由於她曾參加過反送中活動，引發不少示威者質疑事件與警方有關，近日成為社會\n爭論焦點。 警方則一再表示，經調查後證實陳彥霖為自殺，死因無可疑 ..."}, {"title": "印度的絕望之女：全球自殺女性37％在印度，為什麼？ | 過去24小時 ...", "content": "2019年7月26日 ... 與此同時，國際醫學期刊《刺胳針》（The Lancet）也指出，印度婦女自殺人數居全球之\n冠——全世界自殺女性中，有37%來自印度。從母親墮胎殺女嬰到 ..."}, {"title": "巴基斯坦清真寺晚禱時遭自殺炸彈攻擊至少15死19傷| 國際焦點| 全球 ...", "content": "2020年1月11日 ... 法新社報導，這起自殺攻擊案發生在奎達鎮（Quetta），現場滿佈瓦礫和玻璃碎片。 \n參與晚禱的信眾穆罕默德（Fida Mohammad）說，這間清真寺遭到攻擊 ..."}, {"title": "躍下天空步道男大峽谷自殺| 美國新聞| 全球| 聯合新聞網", "content": "2019年9月30日 ... 大峽谷國家公園的西峽谷（Grand Canyon West）28日發生一起自殺事件。一名男子\n在著名旅遊勝地-大峽谷天空步道(Grand Canyon Skywalk)攀過 ..."}, {"title": "少女淫魔艾普斯坦獄中上吊自殺解除監控疑點重重| 美國新聞| 全球 ...", "content": "2019年8月11日 ... 因誘姦少女並用以招待權貴，正在紐約市拘留所中等待審判的金融富豪艾普斯坦(\nJeffrey Epstein)，10日清晨被發現死在監牢裡，「顯然自殺」，立刻 ..."}, {"title": "曾多次來台的美國名廚波登自殺身亡，享壽61歲｜天下雜誌", "content": "2018年6月8日 ... 廣受觀眾喜愛的美國名廚、《波登闖異地》節目主持人波登（Anthony Bourdain）8日\n晚間被證實已自殺身亡，享壽61歲。"}, {"title": "影／夫妻吵架夫持刀刺死妻再自殺1死1傷2幼兒目擊驚哭| 焦點事件 ...", "content": "2020年4月29日 ... 台中市沙鹿區今天發生夫殺妻命案，31歲李姓男子與妻吵架，涉嫌拿水果刀猛刺妻10\n多刀，警方到場噴辣椒水制伏前，男子已持刀自殺，內臟外漏，2 ..."}, {"title": "又失言？柯文哲：自殺拜託吃安眠藥、要自焚去河濱公園- 政治- 自由 ...", "content": "2019年10月18日 ... 台北市長柯文哲昨晚於打臉名嘴粉絲見面會上，指很多火災成因是自焚，他拜託自殺\n者要吃安眠藥、自焚要去河濱公園等說法，又涉失言，遭質疑有 ..."}, {"title": "柯P稱「自殺拜託吃安眠藥」 粉專怒轟：醫師誓詞唸去哪了- 政治- 自由 ...", "content": "2019年10月19日 ... 民眾黨黨主席、台北市長柯文哲17日在「打臉名嘴粉絲見面會」上說，「自殺能不能去\n河濱公園自焚？不要在公寓裡面自焚」，更將憂鬱症與吸毒、酗酒、 ..."}, {"title": "武漢肺炎》院內8人感染新冠病毒死亡英國女護理師不堪重負自殺| 政治 ...", "content": "2020年3月25日 ... 武漢肺炎疫情肆虐全球，各國醫護人員同樣肩負沉重壓力。任職於英國倫敦一間醫院\n加護病房的年約20多歲女護理師，於23日自殺身亡，她任職的 ..."}, {"title": "中國「自殺式公關」毀形象法學者：提醒歐洲與台灣共享價值| 國際焦點 ...", "content": "2020年5月4日 ... 新冠肺炎疫情揭露歐盟與中國間的矛盾。法國學者波恩達茲表示，北京的「自殺式\n公關」讓歐洲重新檢視與中國的關係，台灣史無前例的..."}, {"title": "269旅中尉排長輕生陸軍：3軍官停職調查| 政治| 重點新聞| 中央社CNA", "content": "2020年4月29日 ... 陸軍269旅黃姓中尉排長自殺身亡，陸軍今天晚間表示，除全力配合司法調查外，並\n已組成專案小組行政調查；後勤副旅長陳姓上校、後勤科長趙姓中 ..."}, {"title": "槓上高雄市政府苦苓發表「不道歉、不自殺聲明」 | 政治| 新頭殼Newtalk", "content": "2020年1月21日 ... 苦苓今（21）日發表「不道歉及不自殺聲明書」，自己是基於明確事實、且合理推斷的\n論述，完全可受社會公評，不需要向高市府道歉。苦苓透過臉書表示 ..."}, {"title": "南韓為何自殺的人偏多？ 網點出韓國恐怖民族特性| 生活| 三立新聞網 ...", "content": "2019年11月25日 ... 請繼續往下閱讀…. 韓國,自殺,具荷拉,雪莉,藝人,霸凌,. △有人在 ..."}, {"title": "鮮麗色彩下的憂鬱Kate Spade上吊自殺｜天下雜誌", "content": "2018年6月6日 ... 美國包包配件品牌創辦人Kate Spade，於紐約自宅自殺。誰也想不到在那些明亮色彩\n設計之下，是創辦人極力隱藏的憂鬱。她走了，留下遺書告訴 ..."}, {"title": "柯文哲「自殺拜託吃安眠藥」 王世堅：請松德院長診斷柯的精神問題 ...", "content": "2019年10月18日 ... 自殺就算了，拜託你吃安眠藥，不要用自焚的」，此話一出引發議論，柯文哲今(18)日\n解釋，「有些自殺的方式會造成社會不安，終究是要減少自殺」，對 ..."}, {"title": "殺敵還是慢性自殺火箭仍需證明的冠軍文化- NBA - 籃球| 運動視界 ...", "content": "2020年2月10日 ... 殺敵還是慢性自殺火箭仍需證明的冠軍文化. 儘管已經傳了許久，但當休士頓選擇將\nClint Capela送走換來Robert Covington後，依舊在今年十分平淡 ..."}, {"title": "台中出租套房驚傳三屍命案自殺或他殺待釐清| 台中母嬰三屍案| 社會 ...", "content": "2019年11月7日 ... 台中市警局第一分局偵查隊隊長卓家興表示，目前已知遺體是一大兩小，但案情是\n他殺或自殺，有待警方進一步釐清，目前尚不便說明。 台中地檢署襄閱 ..."}, {"title": "被罵「蠢材、去死」前豐田職員自殺職災認定成立| 全球財經| 全球| 聯合 ...", "content": "2019年11月19日 ... 日本媒體19日報導，一名28歲的豐田汽車職員因遭上司霸凌，數個月來不斷被「笨蛋\n、蠢材、死了比較好」等言詞羞辱，因此自殺。..."}, {"title": "疫情衝擊身心澳洲自殺人數可能激增50% 美國恐不樂觀| 新冠肺炎全球 ...", "content": "2020年5月8日 ... 澳洲最新研究指出，新冠肺炎疫情導致心理和財務壓力，澳洲自殺死亡人數最多可能\n上升50%。另外，美國迄今已有3000多萬人因..."}, {"title": "足球》確診武漢肺炎後自殺身亡法甲蘭斯隊醫留遺書- 自由體育", "content": "2020年4月6日 ... 武漢肺炎全球大爆發，同時疫情也籠罩法國，日前確診染疫的法甲蘭斯隊醫B.岡薩雷\n茲（Bernard Gonzalez），今傳出在家自殺身亡並留下遺書， ..."}, {"title": "驚傳兒子謝維洲自殺住院？ 謝長廷駁斥：假消息- 政治- 自由時報電子報", "content": "2019年8月4日 ... 有流言傳我國駐日大使謝長廷的兒子謝維洲自殺住院，媒體今天（4日）不斷查證此一\n消息。對此，謝長廷今晚駁斥假消息，表示兒子因為政途不順， ..."}, {"title": "自殺高峰！ 「被霸凌不如死」 日本開學日成學生自殺魔咒", "content": "2019年9月2日 ... 9月1日是日本的開學日，日本自殺總和對策中心日前公布1973年至2015年的統計\n發現，9月1日是日本18歲以下的學生自殺率最高的一天！日本許多 ..."}, {"title": "喀布爾婚禮會場自殺炸彈攻擊伊斯蘭國宣稱犯案| 國際焦點| 全球| 聯合 ...", "content": "2019年8月18日 ... 阿富汗首都喀布爾一個結婚禮堂昨晚遭到自殺炸彈攻擊，造成至少63死、182人受傷\n，是喀布爾近幾個月死傷最慘重的一次攻擊，伊..."}, {"title": "想不開？日本肺炎撤僑隔離設施一內閣官房職員疑自殺| 武漢肺炎全球 ...", "content": "2020年2月1日 ... 日本NHK報導，埼玉縣和光市一處暫時收住因肺炎疫情返國僑民的設施中，發現一名\n男職員1日上午倒臥血泊中死亡，經初步調查不排除自殺可能性。"}, {"title": "管仁健觀點》台灣最出名的軍人自殺與冥婚事件| 政治| 新頭殼Newtalk", "content": "2016年5月7日 ... 從歷史來看，台灣最出名的軍人自殺與冥婚事件，應該就是1968年爆發，現今仍\n撲朔迷離的高成器吳純純相約殉情案。 黨外出身的台北市長高玉樹， ..."}, {"title": "謝長廷否認謝維洲自殺住院「他正努力過著常人生活」 | 政治| 要聞| 聯合 ...", "content": "2019年8月5日 ... 駐日代表謝長廷否認兒子、前台北市議員謝維洲自殺住院。他表示，謝維洲離開政治\n圈，正努力過著平常人的生活。 謝長廷昨晚在臉..."}, {"title": "她PO不自殺聲明揭張紫妍與3上吊女星恐怖共通點… - 娛樂- 中時電子報", "content": "2019年3月29日 ... 韓國女星張紫妍10年前自殺身亡，死前更留下血淚遺書指控被逼陪睡換取工作，至今\n真相仍石沉大海。身為張紫妍案唯一證人兼昔日同門師妹的女星 ..."}, {"title": "俄教授承認肢解學生情人本想扮成拿破崙自殺| 世界萬象| 全球| 聯合 ...", "content": "2019年11月10日 ... 索科洛夫著有多本有關法國政治及軍事領袖拿破崙的書，曾擔任多部影片的歷史顧問\n。他於2003年獲頒法國榮譽軍團勳章。 自殺，不能解決難題；求助， ..."}, {"title": "f(x) 雪莉生前的呼救我們都沒聽到：「伸手救援也沒人抓住我的手，我說 ...", "content": "2019年10月14日 ... 雪莉自殺. IG@jelly_jilli. 韓國女團f(x)前成員雪莉（Sulli，本名崔真理）今天（10/14）\n下午被經紀人發現上吊陳屍在自己家中，人生就這樣定格在花樣 ..."}, {"title": "父因她追星自殺亡劉德華狂粉罕見回應「不是我責任」 - 娛樂- 中時電子報", "content": "2018年11月10日 ... 天王劉德華（華仔）出道37年，因優質形象至今人氣不墜，然2007年曾發生一起狂粉\n楊麗娟父親因女兒過度追星自殺而亡的事件，11年過去，最近有 ..."}, {"title": "新北單親媽攜2子女旅館輕生2童餵藥亡、母送醫| 焦點事件| 社會| 聯合 ...", "content": "2020年2月16日 ... ... 林昭彰／新北即時報導 汽車旅館. 新北市今天清晨驚傳離婚母親攜子投宿摩鐵餵\n藥自殺，2童死亡母親送醫，警方封鎖現場調查。記者林昭彰/翻攝 ..."}, {"title": "總統專機飛北京觸法羅智強：她教唆軍公教自殺要辦嗎| 政治| 要聞 ...", "content": "2019年8月9日 ... 林姓男子在臉書多個社團發表「蔡總統出訪友邦，華航機師直接將飛機往北京降落…」\n言論，法務部調查局認為危害總統及國家安全，..."}, {"title": "1年帶你住帝寶詐騙保全血本無歸自殺- 社會- 中時", "content": "2019年7月24日 ... 前年18歲的張姓女子以「一年內帶你入住帝寶」等語，誘騙擔任保全的李姓男子借\n高利貸投資卻血本無歸，李因而自殺死亡；一審依詐欺罪將張女判刑1 ..."}, {"title": "影／軍方說「只寫人名」！中尉排長自殺真相畫在手心「3滴血刀+一隻 ...", "content": "2020年5月6日 ... 時代力量「誠實面對還原真相」記者會269旅黃. ○ 《ETtoday新聞雲》提醒您，請給\n自己機會： 自殺防治諮詢安心專線：0800-788995；生命線協談專線： ..."}, {"title": "助安置武漢返國人士日內閣祕書處職員自殺| 國際| 重點新聞| 中央社CNA", "content": "2020年2月2日 ... 這些民眾日前從武漢搭乘日本政府安排的專機返國，逃避正在湖北省及中國其他各地\n肆虐的新冠狀病毒肺炎疫情。 警方初步認為這名男子是自殺，將 ..."}, {"title": "《自殺突擊隊》懶人包！ 11主角人物介紹＆主視覺海報| ETtoday看電影 ...", "content": "2016年6月24日 ... 電影《自殺突擊隊》24日一口氣曝光所有主要角色的電影視覺的海報版與塗鴉版，\n合共11款人物的視覺，同時曝光這些角色的人物簡介，要讓影迷們在 ..."}, {"title": "武漢肺炎》壓力過大想不開？ 日本承辦武漢撤僑官員墜樓身亡| 國際| 新 ...", "content": "2020年2月1日 ... ... 在埼玉縣跳樓自殺身亡，是否是因壓力過大導致，警方目前正在調查中。 ... 跳樓\n自殺身亡，事發地點是武漢市撤離回日本公民入住的國立保健醫療 ..."}, {"title": "做空比特幣慘賠4.6億！中國比特易創辦人傳自殺身亡- 自由財經", "content": "2019年6月12日 ... 中國知名區塊鏈市場數據分析與服務平台「比特易」的創辦人惠軼，傳出在本月5日\n自殺身亡，享年42歲。（圖擷取自百度） 〔財經頻道／綜合報導〕中國 ..."}, {"title": "外交官自殺家屬指非關假新聞！蘇啟誠寧死不屈- 政治要聞- 中國時報", "content": "2018年12月21日 ... 外交部對日本關西機場事件檢討至今，駐日代表謝長廷始終認為，是假新聞造成駐\n大阪辦事處前處長蘇啟誠自殺。不過，蘇啟誠遺孀昨出面駁斥部分 ..."}, {"title": "砍掉重練的《自殺突擊隊》確定9月開拍：不只小丑女回歸，演員陣容超有 ...", "content": "2019年6月28日 ... 記得年初才吵得火熱的《星際異攻隊》導演詹姆斯岡恩（James Gunn）被爆將執導DC\n《自殺突擊隊》（The Suicide Squad）全新電影，而當時被指出是要 ..."}, {"title": "傅達仁安樂死壽險賠不賠？ | 《現代保險》雜誌", "content": "2018年6月12日 ... 壽險業者及學者均表示，安樂死等同於自殺，比照《保險法》第109條處理。 前體育\n主播傅達仁，7日在瑞士安樂死機構的協助下，劃下生命句點，享壽85 ..."}, {"title": "名廚安東尼波登自殺身亡…扛大批債務認：每晚恐懼朝我襲來| 國際 ...", "content": "2018年6月8日 ... 美國知名主廚、主持人安東尼波登（Anthony Bourdain）今（8）日驚傳自殺身亡，他被\n發現陳屍在法國一家飯店，享壽61歲，死訊曝光震驚外界。安東尼 ..."}, {"title": "史上最兇殘邪教「瓊斯鎮慘案」 908人集體自殺的驚人內幕| 網路人氣 ...", "content": "2019年1月25日 ... ... 與擁戴做盡壞事，著名的事件包括「瓊斯鎮慘案」，這個邪教竟然引發了908人集體\n自殺，是美國史上除了911事件外，第二嚴重的非自然死亡案件…"}, {"title": "神學士又作案自殺炸彈卡車攻擊醫院20死| 國際焦點| 全球| 聯合新聞網", "content": "2019年9月19日 ... 阿富汗南部札布爾省首府卡拉特（Qalat）19日發生自殺炸彈攻擊，裝載炸彈的卡車在\n一間醫院外引爆，造成20人死亡，罹難..."}, {"title": "Netflix影集漢娜的遺言與自殺率關聯研究找答案| 娛樂| 中央社CNA", "content": "2019年4月30日 ... 本劇講述一名青少女為何做出走上絕路的決定。 然而，研究人員表示，這項研究有\n限制，無法直接將自殺率上升與「漢娜的遺言」（13 Reasons Why ..."}, {"title": "女大生含怨亡…悲吐自殺宣言：別折磨我爸媽！關鍵訊息曝「男友逼死 ...", "content": "2020年1月1日 ... 我沒抗住，自殺了，我不承認自己脆弱，我爸媽是農村人，來接我的話別為難他們，別\n折磨他們。」瀋陽一女大生12月28日晚在社交軟體上PO出了人生 ..."}, {"title": "苦苓發不自殺聲明慘遭陳揮文2字酸爆！ - 娛樂- 中時電子報", "content": "2020年1月21日 ... 對此，苦苓在臉書PO出不道歉及不自殺聲明書，強硬回擊高市府提告說，但資深媒體\n人陳揮文今(21日)就忍不住在廣播節目中狠批苦苓此舉是爛哏。"}, {"title": "苦苓不自殺聲明惹攻擊1450帶風向？ - 政治- 中時電子報", "content": "2020年1月22日 ... 舉債議題，作家苦苓與高雄市府隔空交火，相當激烈。高雄市府多次澄清，強硬要求苦\n苓立即道歉，否則將提告。苦苓反擊發表「不道歉及不自殺聲明 ..."}, {"title": "DC證實：《自殺突擊隊》砍掉重練！ 「只剩小丑女」沒有小丑| ETtoday ...", "content": "2019年3月17日 ... 《星際異攻隊》導演詹姆斯岡恩（James Gunn）即將執導DC擴展宇宙《自殺突擊隊》（\nThe Suicide Squad）全新電影，不過並非外界誤解的續集電影《 ..."}, {"title": "名廚安東尼波登自殺身亡傑米奧利佛致哀| 國際| 中央社CNA", "content": "2018年6月8日 ... （中央社記者戴雅真倫敦8日專電）61歲知名主廚、主持人安東尼波登自殺身亡，英國\n名廚傑米奧利佛（Jamie Oliver）在臉書貼出波登的黑白照致哀， ..."}, {"title": "大陸前國家副主席李源潮露面破除自殺謠言| 大陸傳真| 兩岸| 聯合新聞網", "content": "2019年6月26日 ... 李源潮近年的動向頻頻引人揣測，最近網路甚至稱他自殺身亡，中央已介入調查的\n謠言。 多維稱，從照片背景上看，似乎拍攝於一處平房院落裡，隔 ..."}, {"title": "哈利王子舊愛驚爆自殺！死前上傳狗狗合照惹鼻酸- Yahoo奇摩新聞", "content": "2020年2月16日 ... 曾與哈利王子傳出緋聞的英國人氣主持人卡洛琳弗雷克（Caroline Flack），驚爆周六\n於倫敦寓所自殺，終年40歲，死訊已由家人公布。 卡洛琳去年12 ..."}, {"title": "自殺也吹「韓流」？ 加拿大青年遠赴首爾躍漢江：我來自殺的| 羅小編 ...", "content": "2019年1月28日 ... 麻浦大橋橫跨漢江，是連通首爾漢江兩岸的重要橋樑之一，不過這裡卻也成為韓國人\n首選的跳江自殺勝地之一，尤其是政府之後在橋梁護欄加上「累了嗎 ..."}, {"title": "24日香港區議會投票在台港生返鄉前發表「不自殺聲明」 | 中國| 新頭殼 ...", "content": "2019年11月22日 ... 莊強調，台灣選民不需不自殺聲明就能投票，因此，民眾不需對政治冷感，也不用怕\n立場不同就不願討論，畢竟理解、對話才能推動民主進展，鼓勵大家 ..."}, {"title": "中油油輪遭魚雷攻擊？專家：水雷或自殺艇可能性高| 財經焦點| 產經 ...", "content": "... 遭魚雷攻擊？專家：水雷或自殺艇可能性高. 2019-06-13 22:15 聯合報/ 記者\n洪哲政╱即時報導. 兩艘油輪11日在阿曼灣被攻擊，船身起火，船員及時撤離。歐新社\n ..."}, {"title": "雪莉上吊自殺！酸民無止盡的辱罵，是壓垮她的最後一根稻草！", "content": "2019年10月14日 ... 雪莉今（14）日下午驚傳自殺身亡震驚各界，而她生前上節目的片段也一一被挖出，雪\n莉在節目上說到：﻿﻿﻿「但事實上我這樣的生活，就像是個深淵，總是 ..."}, {"title": "「自殺森林」網紅羅根保羅遭Youtube下架新節目喊卡| ETtoday國際 ...", "content": "2018年1月11日 ... 美國網路紅人羅根保羅（Logan Paul）去年底在個人Youtube頻道上傳一段「自殺森林\n」的影片，片中他在日本自殺地點「青木原樹海」發現一具上吊的 ..."}, {"title": "分屍案兇嫌陳屍基隆民宅住戶大驚嚇：昨天才擦身而過| 社會萬象| 社會 ...", "content": "2020年1月12日 ... 林嫌自殺的屋主剛好這幾天不在家，今天回家，發現有人在屋內燒炭身亡，嚇得報警。\n警方到埸比對，確定是林嫌，經查，林以前曾住過這個地方附近，有 ..."}, {"title": "擔心出現自殺模仿潮2008崔真實上吊...同月輕生多3倍| ETtoday星光雲 ...", "content": "2017年12月20日 ... 鐘鉉自殺離世的惡耗在媒體廣泛公布後，從18晚間起整個韓國娛樂圈，也在一片哀傷\n與婉惜的氛圍下，悼念著鐘鉉的逝世。他生前的好友，包括SHINee ..."}, {"title": "南韓N號房40多歲會員跳河自殺遺書稱：沒想到鬧這麼大| 國際焦點 ...", "content": "2020年3月27日 ... 警方將透過可用的監視器影像、男子遺書和男子的親近人士持續調查此案。 自殺，\n不能解決難題；求助，才是最好的路。求救請打1995 ( 要救救我). 疫情 ..."}, {"title": "最血腥1天！油價又自殺24％ 兇手是OPEC老大- 財經- 中時電子報", "content": "2020年3月19日 ... 原本脆弱的原油市場，在OPEC(石油輸出國家組織)老大沙烏地傳出增產消息後，\n油價立馬自殺跳樓，周三(18日)大屠殺逾24%，終場收在20.37美元， ..."}, {"title": "輕奢品牌Kate Spade創始人自殺身亡公司股價一度下跌2% | Anue鉅 ...", "content": "2018年6月6日 ... 警方稱，仍在調查死因，但《時代》雜誌、美聯社等多家媒體認為這是一起明顯的自殺\n事件。 消息流出後，Kate Spade 母公司Tapestry 股價一度下跌超過 ..."}, {"title": "被嫌「不是處女」要拍裸照、流產補償！ 北大高材生被洗腦崩潰自殺 ...", "content": "2019年12月12日 ... 北京大學學生包麗10月服藥自殺，如今躺在醫院病房2個月。包麗的母親爆料稱，\n女兒的男友嫌棄女兒談過戀愛「不是處女」，曾要求拍裸照、先懷孕後 ..."}, {"title": "斯里蘭卡「復活節連續爆炸案」：接連8起自殺炸彈，至少207死| 過去24 ...", "content": "2019年4月21日 ... 斯里蘭卡「復活節連續爆炸案」：接連8起自殺炸彈，至少207死. 南亞國家斯里蘭卡，周\n日發生嚴重的「連環爆炸事件」。當地時間21日9點前後，包括 ..."}, {"title": "拜託自殺吃安眠藥挨批柯文哲今又說：吃安眠藥不會死| 政治| 要聞 ...", "content": "2019年10月29日 ... 台北市長柯文哲日前在打臉名嘴粉絲見面會上，指很多火災成因是自焚，拜託自殺要\n吃安眠藥、自焚要去河濱公園等說法，被指失言。柯..."}, {"title": "影／駐大阪辦事處長蘇啓誠自殺身亡日警在住處拉封鎖線| ETtoday ...", "content": "2018年9月14日 ... ... 待，14日傳出我駐大阪辦事處處長蘇啟誠今天清晨於大阪官邸輕生一事，外交部對\n此一不幸事件表達最深切的悲痛及惋惜(外交部,大阪,颱風,自殺)"}, {"title": "快訊／男「陽明山馬槽橋上」一躍而下！當場慘死…警急將遺體搬上 ...", "content": "2020年1月12日 ... 男馬槽橋上跳下慘死。（圖／記者黃彥傑攝. ○ 《ETtoday新聞雲》提醒您，請給自己\n機會： 自殺防治諮詢安心專線：1925；生命線協談專線：1995."}, {"title": "「國民女友」IU李知恩兩年內痛失兩名摯友，雪莉、鐘鉉相繼輕生後大批 ...", "content": "2019年10月14日 ... F(x)前團員雪莉今日下午被發現於家中上吊自殺，得年25歲。由於退出女子團體後\n較為大膽、放蕩不羈的作風，女星時常遭受部分觀念較為傳統的韓國 ..."}, {"title": "雪莉爆住家2樓自殺身亡客串《德魯納酒店》成遺作... - 娛樂- 中時電子報", "content": "2019年10月14日 ... 不過她今年義氣相挺好友IU，客串夯劇《德魯納酒店》卻難得沒有負評罵聲，讓她也\n相當意外。中時電子報提醒您，自殺解決不了問題，給自己機會： ..."}, {"title": "法甲蘭斯23年資深隊醫確診後自殺身亡與妻一起隔離2周留遺書 ...", "content": "2020年4月6日 ... 法甲勁旅蘭斯隊醫岡薩雷斯確診新冠肺炎後自殺身亡。（圖／翻攝自推特／Stade de \nReims）. 記者游郁香／綜合報導. 新冠肺炎(COVID-19)疫情重創 ..."}, {"title": "東京著衣改名重新出發，創辦人周品均：根本是自殺行為｜數位時代", "content": "2019年7月10日 ... 然而，聽到此消息後，東京著衣創辦人周品均公開在Facebook上表示：「改掉東京著\n衣這四個字，基本上是個自殺行為。」 YOCO Collection目前旗下有 ..."}, {"title": "郭台銘退黨是自殺他殺？ 唐湘龍：待明年政治驗屍| 總統大選觀測站 ...", "content": "2019年9月13日 ... 資深媒體人唐湘龍早上在他的電台節目中指出，郭台銘此時退黨，不管自殺或他殺，\n還沒有蓋棺論定，等明年選完後，讓政治驗屍官去評斷。"}, {"title": "「近乎自殺！」 比特大陸驚爆大裁員50％ - 自由財經", "content": "2020年1月7日 ... 這也是比特大陸共同創辦人吳忌寒在去年10月趕走前董座詹克團後，對於詹克團在\nAI晶片業務任意擴張的「自殺式經營造成天量虧損」，所做出的整頓 ..."}, {"title": "影／尤美女：公投後據通報已有9位同志自殺身亡、23件霸凌| ETtoday ...", "content": "2018年11月30日 ... ... 在這段期間有很多孩子被傷害的體無完膚；公投後，根據通報已經有9位同志自殺\n身亡、2位自殺未遂，還有23件通報霸凌。 (尤美女,同婚,國會直播, ..."}, {"title": "中共上將張陽「自殺」，是死於反貪還是權力鬥爭？ - The News Lens ...", "content": "2017年12月11日 ... （文革期間自殺的上將，是1967年1月隸屬陝北幫的雲南省委第一書記兼昆明軍區第\n一政委的閻紅彥上將。） 而中共的反貪都有強烈的權力鬥爭背景，鬥 ..."}, {"title": "曾跟柯林頓、川普出遊一度叱吒風雲，最後在獄中自殺的艾普斯坦是誰？", "content": "2019年8月11日 ... 被控性侵數十名未成年少女的66歲美國資本家艾普斯坦（Jeffrey Epstein），美國時間\n週六於獄中身亡，目前警方研判為自殺。艾普斯坦惡名昭彰，戀童 ..."}, {"title": "女兒投資挖礦機慘賠輕生父控訴詐團害命- 社會- 自由時報電子報", "content": "2019年6月20日 ... 一名家住台中大里的許姓女子（30歲），今天早上遭家人發現，在房間自殺身亡，許女\n的父親難過愛女年輕生命就這樣結束，今天在臉書「大里人聊天 ..."}, {"title": "《比悲傷更悲傷的故事》韓版比台版更虐心！女主角懷孕自殺、牙醫甘願 ...", "content": "2018年12月10日 ... 女主角懷孕自殺、牙醫甘願「被設計」為愛犧牲. 完全不敢再看韓版《比悲傷更悲傷的\n故事》一次！ By ..."}, {"title": "教唆自殺？少女要網友投票選擇生死69%投死她就跳樓了| 奇聞不要看 ...", "content": "2019年5月15日 ... 在這個國家，自殺未遂是犯罪，教唆自殺也許也有罪。」 馬來西亞媒體報導，這名少女\n13日下午3時許從石角新市鎮3樓店面跳樓自殺。除了在Instagram ..."}, {"title": "管仁健觀點》兩個北一女資優生相約自殺以後| 生活| 新頭殼Newtalk", "content": "2016年12月5日 ... 兩位明星女中的學生一起自殺，遺書中還提到什麼「在社會生存的本質就不適合我們」\n，於是媒體開始帶領讀者一起辦案了。不過說真的，時空不用拉 ..."}, {"title": "打破自殺傳言！親友還原現場與hide 許下「來春之約」 - KKBOX", "content": "2018年8月27日 ... 視覺系傳奇吉他手hide 1998 年逝世，關於他是意外過世亦或是自殺身亡，至今仍是\n一個無解之謎，今年適逢他逝世20 週年推出紀念電影「hide：來 ..."}, {"title": "韓國警方公佈崔雪莉屍檢結果確認死因爲自殺| 新聞- Yahoo奇摩行動版", "content": "2019年10月16日 ... 根據國立科學搜查研究院的屍檢結果，警方確認崔雪莉死於自殺，將以“無公訴權”爲\n由結案。 崔雪莉在本月14日下午3點21分被發現去世，她的經紀人 ..."}, {"title": "「張紫妍自殺案」被勝利風波掩蓋！師妹請求幫忙⋯明星們「怕到噤聲」唯 ...", "content": "2019年3月18日 ... 還記得2009年的「張紫妍自殺案」嗎？近日因為勝利、鄭俊英的「偷拍性愛影片」風波，﻿\n張紫妍案件的最後訴訟期沒有得到相應的關注。﻿她的同門師妹﻿ ..."}, {"title": "股價暴殺也不管！沙國自殺式攻擊美俄挫咧等- 財經- 中時電子報", "content": "股價暴殺也不管！沙國自殺式攻擊美俄挫咧等. 19:302020/03/10. 中時電子報. \n呂承哲. Facebook; Messenger; Line; Weibo; Twitter; Telegram; 複製連結. 這場\n石油版 ..."}, {"title": "好想自殺！空姐變木乃伊八仙塵爆傷者：最痛苦的是爸媽哭了| ETtoday ...", "content": "2018年3月6日 ... 我沒有忘記爸媽臉上的表情，是心疼地緩緩打量這個被包成木乃伊的女兒。人生中的\n每一天，如果能夠平平安安地回家，舒舒服服地躺上床，然後睡去 ..."}, {"title": "林明溱嗆蔡英文：中火讓中部600萬人慢性自殺| 反空汙中火挨罰| 產經 ...", "content": "2019年12月3日 ... 這是蔡英文總統給中部地區600萬人慢性自殺的做法，每天呼吸PM2.5進去，得到肺\n腺癌不知不覺，等到去醫院檢查已經末期，中央再不理會，就發動 ..."}, {"title": "《波登不設限》主持人波登驚傳酒店自殺亡享壽61歲- 娛樂- 中時電子報", "content": "2018年6月8日 ... 知名美食節目《波登不設限》主持人安東尼波登(Anthony Bourdain)驚傳8日法國自殺\n身亡，享壽61歲，具體死因仍在調查中。英國名廚傑米奧利 ..."}]}